{"viewers":[{"id":0,"username":"johnytest136","karma":200,"coins":4023},{"id":1,"username":"nightbot","karma":100,"coins":67409},{"id":2,"username":"druidsunion","karma":110,"coins":0},{"id":3,"username":"exeore21","karma":200,"coins":12224},{"id":4,"username":"dialtone","karma":200,"coins":21937},{"id":5,"username":"deannialynn","karma":400,"coins":0},{"id":6,"username":"gothgwem89","karma":200,"coins":3041},{"id":7,"username":"no_lives_left_","karma":200,"coins":20400},{"id":8,"username":"alliemegan32","karma":100,"coins":0},{"id":9,"username":"rygger_dracora","karma":200,"coins":43358},{"id":10,"username":"esteban_reynolds12","karma":100,"coins":0},{"id":11,"username":"thorycat","karma":500,"coins":0},{"id":12,"username":"danothaman","karma":400,"coins":0},{"id":13,"username":"benderisgreat_34_","karma":200,"coins":25867},{"id":14,"username":"benderisgreat_34_","karma":100,"coins":0},{"id":15,"username":"tiahgamingvt","karma":300,"coins":0},{"id":16,"username":"kgu111","karma":100,"coins":0},{"id":17,"username":"lenzarng","karma":200,"coins":60766},{"id":18,"username":"lenzarng","karma":100,"coins":0},{"id":19,"username":"brogrox96","karma":400,"coins":0},{"id":20,"username":"soundalerts","karma":100,"coins":0},{"id":21,"username":"soundalerts","karma":100,"coins":0},{"id":22,"username":"demnos180","karma":400,"coins":0},{"id":23,"username":"mrben_gaming","karma":100,"coins":0},{"id":24,"username":"littlemsbink","karma":100,"coins":0},{"id":25,"username":"littlemsbink","karma":100,"coins":0},{"id":26,"username":"itsberrymore","karma":100,"coins":0},{"id":27,"username":"itsberrymore","karma":100,"coins":0},{"id":28,"username":"wickedplague","karma":400,"coins":0},{"id":29,"username":"leutiankane","karma":200,"coins":47669},{"id":30,"username":"cowbeeboybop","karma":400,"coins":0},{"id":31,"username":"mouse5252","karma":400,"coins":0},{"id":32,"username":"edg3runn3r_2029","karma":100,"coins":0},{"id":33,"username":"ktisthebest8","karma":400,"coins":0},{"id":34,"username":"ktisthebest8","karma":100,"coins":0},{"id":35,"username":"artic_blizz","karma":100,"coins":0},{"id":36,"username":"artic_blizz","karma":100,"coins":0},{"id":37,"username":"artic_blizz","karma":100,"coins":0},{"id":38,"username":"jayxcompk","karma":100,"coins":0},{"id":39,"username":"jayxcompk","karma":100,"coins":0},{"id":40,"username":"pavel822111","karma":100,"coins":0},{"id":41,"username":"pavel822111","karma":100,"coins":0},{"id":42,"username":"suitald","karma":165,"coins":0},{"id":43,"username":"invisibleman275","karma":200,"coins":23437},{"id":44,"username":"professionmksman","karma":400,"coins":0},{"id":45,"username":"professionmksman","karma":100,"coins":0},{"id":46,"username":"ellidersa1","karma":100,"coins":0},{"id":47,"username":"ellidersa1","karma":100,"coins":0},{"id":48,"username":"dantastic2022","karma":400,"coins":0},{"id":49,"username":"flyingtuah","karma":100,"coins":0},{"id":50,"username":"flyingtuah","karma":100,"coins":0},{"id":51,"username":"6amdaydrinker","karma":400,"coins":0},{"id":52,"username":"citadfls","karma":100,"coins":0},{"id":53,"username":"citadfls","karma":100,"coins":0},{"id":54,"username":"lildyla","karma":400,"coins":0},{"id":55,"username":"embersof1stdynasty","karma":400,"coins":0},{"id":56,"username":"embersof1stdynasty","karma":100,"coins":0},{"id":57,"username":"aramati","karma":100,"coins":0},{"id":58,"username":"aramati","karma":100,"coins":0},{"id":59,"username":"ohwikked","karma":325,"coins":0},{"id":60,"username":"nekorivera","karma":100,"coins":0},{"id":61,"username":"nekorivera","karma":100,"coins":0},{"id":62,"username":"nekorivera","karma":100,"coins":0},{"id":63,"username":"jeffisneat","karma":100,"coins":0},{"id":64,"username":"jeffisneat","karma":100,"coins":0},{"id":65,"username":"hopeful_destroyer","karma":400,"coins":0},{"id":66,"username":"hopeful_destroyer","karma":100,"coins":0},{"id":67,"username":"hopeful_destroyer","karma":100,"coins":0},{"id":68,"username":"ace_alastorr","karma":100,"coins":12250},{"id":69,"username":"ace_alastorr","karma":100,"coins":0},{"id":70,"username":"thicciest_burrito","karma":36,"coins":0},{"id":71,"username":"no_lives_left","karma":100,"coins":0},{"id":72,"username":"mo_zombee","karma":400,"coins":0},{"id":73,"username":"alaskan_kodiak","karma":100,"coins":0},{"id":74,"username":"aboveaveragedavid","karma":100,"coins":8600},{"id":75,"username":"aboveaveragedavid","karma":100,"coins":0},{"id":76,"username":"alicedtrh","karma":400,"coins":0},{"id":77,"username":"twentyonewtf","karma":100,"coins":0},{"id":78,"username":"twentyonewtf","karma":100,"coins":0},{"id":79,"username":"chillgreenbean","karma":200,"coins":13310},{"id":80,"username":"marcos_1berto","karma":100,"coins":9250},{"id":81,"username":"marcos_1berto","karma":100,"coins":1000},{"id":82,"username":"bradusavge","karma":109,"coins":1025},{"id":83,"username":"bradusavge","karma":100,"coins":1000}],"total":84}